PortDebug/__init__.py
PortDebug/main.py
PortDebug-1.0.8.dist-info/METADATA
PortDebug-1.0.8.dist-info/WHEEL
PortDebug-1.0.8.dist-info/entry_points.txt
PortDebug-1.0.8.dist-info/top_level.txt
PortDebug-1.0.8.dist-info/RECORD
